lxml_html_clean/__init__.py
lxml_html_clean/__init__.pyi
lxml_html_clean/clean.py
lxml_html_clean/clean.pyi
lxml_html_clean/py.typed
lxml_html_clean-0.4.0.dist-info/LICENSE.txt
lxml_html_clean-0.4.0.dist-info/METADATA
lxml_html_clean-0.4.0.dist-info/WHEEL
lxml_html_clean-0.4.0.dist-info/top_level.txt
lxml_html_clean-0.4.0.dist-info/RECORD
