Metadata-Version: 2.1
Name: lxml_html_clean
Version: 0.4.0
Summary: HTML cleaner from lxml project
Home-page: https://github.com/fedora-python/lxml_html_clean/
Author: Lumír Balhar
Author-email: lbalhar@redhat.com
License: BSD-3-Clause
Project-URL: Documentation, https://lxml-html-clean.readthedocs.io/
Classifier: Programming Language :: Python :: 3
Classifier: Programming Language :: Python :: 3.6
Classifier: Programming Language :: Python :: 3.7
Classifier: Programming Language :: Python :: 3.8
Classifier: Programming Language :: Python :: 3.9
Classifier: Programming Language :: Python :: 3.10
Classifier: Programming Language :: Python :: 3.11
Classifier: Programming Language :: Python :: 3.12
Classifier: Programming Language :: Python :: 3.13
License-File: LICENSE.txt
Requires-Dist: lxml
